{
  "query": "홍대 분위기 좋은 카페",
  "timestamp": "20250916_005318",
  "total_processed": 5,
  "top_results": [
    {
      "name": "오랜만에 서울 놀러 나가기로 했는데 분위기 좋은 홍대 예쁜 카페 알려주세요!! : 궁금증 해결은 궁금하넷",
      "address": "",
      "image_url": null,
      "mapx": "",
      "mapy": "",
      "review_trust_score": 0,
      "summary_text": "홍대카페 예쁜카페 포토존 사진찍기좋은카페 10대 예쁜 인테리어 사진 찍기 좋은 포토존",
      "summary_pros": [
        "예쁜 인테리어",
        "사진 찍기 좋은 포토존"
      ],
      "summary_cons": [
        "크기가 작을 수 있음",
        "주말 혼잡 가능성"
      ],
      "keywords": [
        "홍대카페",
        "예쁜카페",
        "포토존",
        "사진찍기좋은카페",
        "10대"
      ],
      "signature_menu": "정보 없음",
      "price_range": "정보 없음",
      "opening_hours": "정보 없음",
      "parking": "정보 없음",
      "phone": "정보 없음",
      "nearby_attractions": [
        "홍대입구역",
        "한강"
      ],
      "similarity_score": 0.8305287228596829,
      "final_score": 0.581370106001778,
      "rank": 1
    },
    {
      "name": "분위기 깡패 &#39;마포 맛집&#39;부터 해리포터 명장면을 그대로 재현한 홍대 카페까지? - 콘텐츠뷰",
      "address": "",
      "image_url": null,
      "mapx": "",
      "mapy": "",
      "review_trust_score": 0,
      "summary_text": "마포 맛집 서강팔경 프렌치 요리 전망 좋은 레스토랑 분위기 좋은 레스토랑 홍대 데이트 한강 전망과 독특한 인테리어 남산, 북한산 등 파노라마 뷰 감상 가능 브레이크 타임 없음 낮에는 브런치, 저녁에는 와인 및 칵테일 제공 홍대 데이트 코스로 적합",
      "summary_pros": [
        "한강 전망과 독특한 인테리어",
        "남산, 북한산 등 파노라마 뷰 감상 가능",
        "브레이크 타임 없음",
        "낮에는 브런치, 저녁에는 와인 및 칵테일 제공",
        "홍대 데이트 코스로 적합"
      ],
      "summary_cons": [
        "가격이 다소 높음"
      ],
      "keywords": [
        "마포 맛집",
        "서강팔경",
        "프렌치 요리",
        "전망 좋은 레스토랑",
        "분위기 좋은 레스토랑",
        "홍대 데이트"
      ],
      "signature_menu": "프렌치 요리",
      "price_range": "고가",
      "opening_hours": "정보 없음",
      "parking": "정보 없음",
      "phone": "정보 없음",
      "nearby_attractions": [
        "DMC 문화공원",
        "카페",
        "방탈출",
        "만화카페"
      ],
      "similarity_score": 0.7051521686753304,
      "final_score": 0.4936065180727312,
      "rank": 2
    },
    {
      "name": "수상한베이글 홍대",
      "address": "서울특별시 마포구 와우산로15길 22",
      "image_url": null,
      "mapx": "1269218429",
      "mapy": "375496284",
      "review_trust_score": 0,
      "summary_text": "테라스 맛집 베이글 한우 스테이크 파스타 이탈리안 한식 가성비 분위기 좋은 맛집 데이트 정원이 있어 분위기 좋고 야외 식사 가능 다양하고 맛있는 메뉴 고즈넉하고 편안한 분위기의 공간",
      "summary_pros": [
        "정원이 있어 분위기 좋고 야외 식사 가능",
        "다양하고 맛있는 메뉴",
        "고즈넉하고 편안한 분위기의 공간"
      ],
      "summary_cons": [],
      "keywords": [
        "테라스 맛집",
        "베이글",
        "한우 스테이크",
        "파스타",
        "이탈리안",
        "한식",
        "가성비",
        "분위기 좋은 맛집",
        "데이트"
      ],
      "signature_menu": "베이글, 한우 스테이크, 파스타, 지중해식 문어 구이, 프렌치토스트, 칼국수, 숙성회",
      "price_range": "6,500원~110,000원",
      "opening_hours": null,
      "parking": null,
      "phone": null,
      "nearby_attractions": [],
      "similarity_score": 0.5530561818571877,
      "final_score": 0.3871393273000314,
      "rank": 3
    }
  ]
}